{
  "allquotes": [
    {"quote":"साख बनाने में बीस साल लगते हैं और उसे गंवाने में बस पांच मिनट, अगर आप इस बारे में सोचेंगे तो आप चीजें अलग तरह से करेंगे।", "author": "वॉरेन बफे" },
    {"quote":"कभी मत सोचिये कि आत्मा के लिए कुछ असंभव है, ऐसा सोचना सबसे बड़ा विधर्म है, अगर कोई पाप है, तो वो यही है; ये कहना कि तुम निर्बल हो या अन्य निर्बल हैं।", "author": "स्वामी विवेकानंद"},
    {"quote":"अगर धन दूसरों की भलाई करने में मदद करे, तो इसका कुछ मूल्य है, अन्यथा, ये सिर्फ बुराई का एक ढेर है, और इससे जितना जल्दी छुटकारा मिल जाये उतना बेहतर है।", "author": "स्वामी विवेकानंद"},
    {"quote":"मैं 7 फुट के अवरोध को पार करने की नहीं सोचता: मैं 1 फुट का अवरोध ढूंढता हूँ जिसे मैं पार कर सकूँ।", "author": "वॉरेन बफे"},
    {"quote":"गलतियां हमेशा क्षमा की जा सकती हैं, यदि आपके पास उन्हें स्वीकारने का साहस हो।", "author": "ब्रूस ली"},
    {"quote":"जितना एक मूर्ख वयक्ति किसी बुद्धिमानी भरे उत्तर से नहीं सीख सकता उससे अधिक  एक बुद्धिमान एक मूर्खतापूर्ण प्रश्न से सीख सकता है।", "author": "ब्रूस ली"},
    {"quote":"जैसा आप सोचते हैं, वैसा आप बन जायेंगे।", "author": "ब्रूस ली"},
    {"quote":"खुश रहो लेकिन कभी संतुष्ट मत रहो।", "author": "ब्रूस ली"}

  ]
}

